traceai_bedrock/__generated__/__init__.py
traceai_bedrock/__generated__/anthropic/__init__.py
traceai_bedrock/__generated__/anthropic/_types.py
traceai_bedrock/__init__.py
traceai_bedrock/_attribute_extractor.py
traceai_bedrock/_proxy.py
traceai_bedrock/_rag_wrappers.py
traceai_bedrock/_response_accumulator.py
traceai_bedrock/_trace_collector.py
traceai_bedrock/_wrappers.py
traceai_bedrock/package.py
traceai_bedrock/utils/__init__.py
traceai_bedrock/utils/_extract_invoke_model_attributes.py
traceai_bedrock/utils/anthropic/__init__.py
traceai_bedrock/utils/anthropic/_attributes.py
traceai_bedrock/utils/anthropic/_messages.py
traceai_bedrock/utils/json_utils.py
traceai_bedrock/version.py
traceai_bedrock-0.1.9.dist-info/METADATA
traceai_bedrock-0.1.9.dist-info/WHEEL
traceai_bedrock-0.1.9.dist-info/RECORD
