Metadata-Version: 2.3
Name: traceAI-bedrock
Version: 0.1.9
Summary: OpenTelemetry instrumentation for Bedrock
Author: Future AGI
Author-email: no-reply@futureagi.com
Requires-Python: >3.10,<3.14
Classifier: Programming Language :: Python :: 3
Classifier: Programming Language :: Python :: 3.11
Classifier: Programming Language :: Python :: 3.12
Classifier: Programming Language :: Python :: 3.13
Requires-Dist: boto3 (>=1.38.17)
Requires-Dist: botocore
Requires-Dist: dacite (>=1.8.1)
Requires-Dist: fi-instrumentation-otel (>=0.1.11)
